superflexpy/__init__.py
superflexpy/framework/__init__.py
superflexpy/framework/element.py
superflexpy/framework/network.py
superflexpy/framework/node.py
superflexpy/framework/unit.py
superflexpy/implementation/__init__.py
superflexpy/implementation/computation/__init__.py
superflexpy/implementation/computation/pegasus_root_finding.py
superflexpy/implementation/elements/__init__.py
superflexpy/implementation/elements/gr4j.py
superflexpy/implementation/elements/hbv.py
superflexpy/implementation/elements/structure_elements.py
superflexpy/implementation/elements/thur_model_hess.py
superflexpy/utils/__init__.py
superflexpy/utils/common_class.py
superflexpy/utils/generic_component.py
superflexpy/utils/root_finder.py
superflexpy-0.3.0.dist-info/AUTHORS
superflexpy-0.3.0.dist-info/LICENSE
superflexpy-0.3.0.dist-info/METADATA
superflexpy-0.3.0.dist-info/WHEEL
superflexpy-0.3.0.dist-info/top_level.txt
superflexpy-0.3.0.dist-info/RECORD
