Metadata-Version: 2.1
Name: superflexpy
Version: 0.3.0
Summary: Framework for building hydrological models
Home-page: UNKNOWN
Author: Marco Dal Molin
Author-email: marco.dalmolin.1991@gmail.com
License: Apache Software License
Platform: UNKNOWN
Classifier: Development Status :: 3 - Alpha
